{
    "afar": "aa",
    "afrikaans": "af",
    "akan": "ak",
    "albanian": "sq",
    "amharic": "am",
    "arabic": "ar",
    "aragonese": "an",
    "armenian": "hy",
    "assamese": "as",
    "avaric": "av",
    "avestan": "ae",
    "aymara": "ay",
    "azerbaijani": "az",
    "bambara": "bm",
    "bashkir": "ba",
    "basque": "eu",
    "belarusian": "be",
    "bengali": "bn",
    "bislama": "bi",
    "bosnian": "bs",
    "breton": "br",
    "bulgarian": "bg",
    "burmese": "my",
    "castilian": "es",
    "catalan": "ca",
    "central": "khmer",
    "chamorro": "ch",
    "chechen": "ce",
    "chewa": "ny",
    "chichewa": "ny",
    "chinese": "zh",
    "chuang": "za",
    "chuvash": "cv",
    "cornish": "kw",
    "corsican": "co",
    "cree": "cr",
    "croatian": "hr",
    "czech": "cs",
    "danish": "da",
    "dhivehi": "dv",
    "divehi": "dv",
    "dutch": "nl",
    "dzongkha": "dz",
    "english": "en",
    "esperanto": "eo",
    "estonian": "et",
    "ewe": "ee",
    "faroese": "fo",
    "fijian": "fj",
    "finnish": "fi",
    "flemish": "nl",
    "french": "fr",
    "fulah": "ff",
    "gaelic": "gd",
    "galician": "gl",
    "ganda": "lg",
    "georgian": "ka",
    "german": "de",
    "gikuyu": "ki",
    "greenlandic": "kl",
    "guarani": "gn",
    "gujarati": "gu",
    "haitian": "ht",
    "haitian": "creole",
    "hausa": "ha",
    "hebrew": "he",
    "herero": "hz",
    "hindi": "hi",
    "hiri": "motu",
    "hungarian": "hu",
    "icelandic": "is",
    "ido": "io",
    "igbo": "ig",
    "indonesian": "id",
    "interlingue": "ie",
    "inuktitut": "iu",
    "inupiaq": "ik",
    "irish": "ga",
    "italian": "it",
    "japanese": "ja",
    "javanese": "jv",
    "kalaallisut": "kl",
    "kannada": "kn",
    "kanuri": "kr",
    "kashmiri": "ks",
    "kazakh": "kk",
    "kikuyu": "ki",
    "kinyarwanda": "rw",
    "kirghiz": "ky",
    "komi": "kv",
    "kongo": "kg",
    "korean": "ko",
    "kuanyama": "kj",
    "kurdish": "ku",
    "kwanyama": "kj",
    "kyrgyz": "ky",
    "lao": "lo",
    "latin": "la",
    "latvian": "lv",
    "letzeburgesch": "lb",
    "limburgan": "li",
    "limburger": "li",
    "limburgish": "li",
    "lingala": "ln",
    "lithuanian": "lt",
    "luxembourgish": "lb",
    "macedonian": "mk",
    "malagasy": "mg",
    "malay": "ms",
    "malayalam": "ml",
    "maldivian": "dv",
    "maltese": "mt",
    "manx": "gv",
    "maori": "mi",
    "marathi": "mr",
    "marshallese": "mh",
    "moldavian": "ro",
    "moldovan": "ro",
    "mongolian": "mn",
    "nauru": "na",
    "navaho": "nv",
    "navajo": "nv",
    "ndonga": "ng",
    "nepali": "ne",
    "nuosu": "ii",
    "nyanja": "ny",
    "occidental": "ie",
    "ojibwa": "oj",
    "oriya": "or",
    "oromo": "om",
    "ossetian": "os",
    "ossetic": "os",
    "pali": "pi",
    "panjabi": "pa",
    "pashto": "ps",
    "persian": "fa",
    "polish": "pl",
    "portuguese": "pt",
    "punjabi": "pa",
    "pushto": "ps",
    "quechua": "qu",
    "romanian": "ro",
    "romansh": "rm",
    "rundi": "rn",
    "russian": "ru",
    "samoan": "sm",
    "sango": "sg",
    "sanskrit": "sa",
    "sardinian": "sc",
    "serbian": "sr",
    "shona": "sn",
    "sichuan": "yi",
    "sindhi": "sd",
    "sinhala": "si",
    "sinhalese": "si",
    "slovak": "sk",
    "slovenian": "sl",
    "somali": "so",
    "spanish": "es",
    "sundanese": "su",
    "swahili": "sw",
    "swati": "ss",
    "swedish": "sv",
    "tagalog": "tl",
    "tahitian": "ty",
    "tajik": "tg",
    "tamil": "ta",
    "tatar": "tt",
    "telugu": "te",
    "thai": "th",
    "tibetan": "bo",
    "tigrinya": "ti",
    "tsonga": "ts",
    "tswana": "tn",
    "turkish": "tr",
    "turkmen": "tk",
    "twi": "tw",
    "uighur": "ug",
    "ukrainian": "uk",
    "urdu": "ur",
    "uyghur": "ug",
    "uzbek": "uz",
    "valencian": "ca",
    "venda": "ve",
    "vietnamese": "vi",
    "walloon": "wa",
    "welsh": "cy",
    "wolof": "wo",
    "xhosa": "xh",
    "yiddish": "yi",
    "yoruba": "yo",
    "zhuang": "za",
    "zulu": "zu"
}
